cidt/__init__.py
cidt/decorators/singleton.py
cidt/utils/dialog.py
cidt-0.1.1.dist-info/WHEEL
cidt-0.1.1.dist-info/entry_points.txt
cidt-0.1.1.dist-info/METADATA
cidt-0.1.1.dist-info/RECORD
